pdb.py
setup.py
wdb_over_pdb.egg-info/PKG-INFO
wdb_over_pdb.egg-info/SOURCES.txt
wdb_over_pdb.egg-info/dependency_links.txt
wdb_over_pdb.egg-info/requires.txt
wdb_over_pdb.egg-info/top_level.txt