Metadata-Version: 1.0
Name: wdb-over-pdb
Version: 0.0
Summary: Hack to force use of wdb over pdb (Useful for thing like py.test --pdb)
Home-page: http://github.com/Kozea/wdb
Author: Florian Mounier @ kozea
Author-email: florian.mounier@kozea.fr
License: GPLv3
Platform: UNKNOWN
